{
  "卦名": "大壮卦",
  "卦辞": "利贞",
  "象曰": "雷在天上，大壮。君子以非礼弗履",
  "时运": "成名不难，不可骄傲",
  "财运": "得价即售，不可过贪",
  "家宅": "小心防火；相敬如宾",
  "身体": "保养脚部",
  "动爻": [
    {
      "爻位": "初九",
      "爻辞": "壮于趾，征凶，有孚",
      "象曰": "壮于趾，其孚穷也",
      "时运": "有勇无谋，功名必卑",
      "财运": "不能慎思，必遭损失",
      "家宅": "不可迁移；防女足疾",
      "身体": "慎择良医"
    },
    {
      "爻位": "九二",
      "爻辞": "贞吉",
      "象曰": "九二贞吉，以中也",
      "时运": "中庸处世，受到肯定",
      "财运": "货价合宜，自然获利",
      "家宅": "地位适中；婚姻吉祥",
      "身体": "滋补得宜"
    },
    {
      "爻位": "九三",
      "爻辞": "小人用壮，君子用罔，贞厉。羝羊触藩，羸其角",
      "象曰": "小人用壮，君子罔也",
      "时运": "临事而惧，谦退受益",
      "财运": "不必垄断，否则大耗",
      "家宅": "过高易震；夫妻反目",
      "身体": "血气过刚，防有不测"
    },
    {
      "爻位": "九四",
      "爻辞": "贞吉悔亡，藩决不羸，壮于大舆之輹",
      "象曰": "藩决不羸，尚往也",
      "时运": "前途无阻，功名亦显",
      "财运": "满载而归，何乐不为",
      "家宅": "赶快整修；不是佳偶",
      "身体": "恐有不测"
    },
    {
      "爻位": "六五",
      "爻辞": "丧羊于易，无悔",
      "象曰": "丧羊于易，位不当也",
      "时运": "亡羊补牢，晚年有望",
      "财运": "恐有小失，尚无大碍",
      "家宅": "不宜畜牧；婚礼不成",
      "身体": "不吉之象"
    },
    {
      "爻位": "上六",
      "爻辞": "羝羊触藩，不能退，不能遂，无攸利。艰则吉",
      "象曰": "不能退，不能遂，不详也；艰则吉，咎不长也",
      "时运": "早些退休，以免后悔",
      "财运": "原想发财，难以保本",
      "家宅": "艰难自守；先苦后乐",
      "身体": "进退两难"
    }
  ]
}